cloud_storage_manager/__init__.py
cloud_storage_manager/aws_s3_storage.py
cloud_storage_manager/base_storage.py
cloud_storage_manager/exceptions.py
cloud_storage_manager/gcp_storage.py
cloud_storage_manager/storage_provider.py
cloud_storage_manager/storage_schema.py
cloud_storage_manager-0.1.2.dist-info/LICENSE
cloud_storage_manager-0.1.2.dist-info/METADATA
cloud_storage_manager-0.1.2.dist-info/WHEEL
cloud_storage_manager-0.1.2.dist-info/top_level.txt
cloud_storage_manager-0.1.2.dist-info/RECORD
