Metadata-Version: 2.2
Name: cloud-storage-manager
Version: 0.1.2
Summary: A unified interface for AWS S3 and Google Cloud Storage operations
Home-page: https://github.com/10XScale-in/cloud-storage-manager
Author: MUTHARASU
Author-email: MUTHARASU A <mutharasu39@gmail.com>
License: MIT License  
Project-URL: Homepage, https://github.com/10XScale-in/cloud-storage-manager
Project-URL: Bug Tracker, https://github.com/10XScale-in/cloud-storage-manager/issues
Keywords: aws,s3,gcp,cloud storage,file upload,async
Classifier: Development Status :: 3 - Alpha
Classifier: Intended Audience :: Developers
Classifier: License :: OSI Approved :: MIT License
Classifier: Programming Language :: Python :: 3
Classifier: Programming Language :: Python :: 3.8
Classifier: Programming Language :: Python :: 3.9
Classifier: Programming Language :: Python :: 3.10
Classifier: Programming Language :: Python :: 3.11
Classifier: Framework :: AsyncIO
Classifier: Topic :: Internet :: File Transfer Protocol (FTP)
Classifier: Topic :: Software Development :: Libraries :: Python Modules
Requires-Python: >=3.8
License-File: LICENSE
Requires-Dist: aioboto3>=11.0.0
Requires-Dist: google-cloud-storage>=2.0.0
Requires-Dist: pydantic>=2.0.0
Provides-Extra: dev
Requires-Dist: pytest>=7.0.0; extra == "dev"
Requires-Dist: pytest-asyncio>=0.20.0; extra == "dev"
Requires-Dist: mypy>=1.0.0; extra == "dev"
Requires-Dist: black>=22.0.0; extra == "dev"
Requires-Dist: isort>=5.0.0; extra == "dev"
Requires-Dist: flake8>=6.0.0; extra == "dev"
